teyvatapi/__init__.py
teyvatapi/api_client.py
teyvatapi/api_response.py
teyvatapi/configuration.py
teyvatapi/exceptions.py
teyvatapi/py.typed
teyvatapi/rest.py
teyvatapi/api/__init__.py
teyvatapi/api/book_api.py
teyvatapi/api/paimon_api.py
teyvatapi/api/user_api.py
teyvatapi/models/__init__.py
teyvatapi/models/book.py
teyvatapi/models/create_user_request_body.py
teyvatapi/models/delete_user_request_body.py
teyvatapi/models/email_update_request_body.py
teyvatapi/models/get_prompt_request_body.py
teyvatapi/models/login_request_body.py
teyvatapi/models/password_update_request_body.py
teyvatapi/models/problem_details.py
teyvatapi/models/user.py
teyvatapi/models/username_update_request_body.py
teyvatapi-1.0.1.dist-info/METADATA
teyvatapi-1.0.1.dist-info/WHEEL
teyvatapi-1.0.1.dist-info/top_level.txt
teyvatapi-1.0.1.dist-info/RECORD
